starlette_abstract/__init__.py
starlette_abstract/middleware.py
starlette_abstract-0.0.1.dist-info/LICENSE
starlette_abstract-0.0.1.dist-info/METADATA
starlette_abstract-0.0.1.dist-info/WHEEL
starlette_abstract-0.0.1.dist-info/top_level.txt
starlette_abstract-0.0.1.dist-info/RECORD
