Metadata-Version: 2.1
Name: starlette-abstract
Version: 0.0.1
Summary: An abstract middleware for Starlette
Author-email: Sebastian Balna <sebastianbalna@gmail.com>
License: Copyright (c) 2022 Sebastian Balna        
Project-URL: Homepage, https://github.com/zaxis23148/starlette_abstract
Project-URL: Bug Tracker, https://github.com/zaxis23148/starlette_abstract/issues
Classifier: Programming Language :: Python :: 3
Classifier: License :: OSI Approved :: MIT License
Classifier: Operating System :: OS Independent
Requires-Python: >=3.7
License-File: LICENSE
